{
    "id": "798",
    "name": "Joshua Gilbrech",
    "nationality": "United States",
    "categories": [
        "Longsword (Mixed & Men's, Nylon)",
        "Longsword (Mixed & Men's, Steel)",
        "Rapier and Dagger (Mixed, Steel)",
        "Sabre (Mixed & Men's, Steel)",
        "Single Rapier (Mixed, Steel)",
        "Singlestick (Mixed)"
    ],
    "ratings": [
        "1272.2",
        "1609.1",
        "1256.8",
        "940.2",
        "1234.1",
        "1516.7"
    ],
    "rankings": [
        "192",
        "194",
        "452",
        "1832",
        "598",
        "42"
    ],
    "club_id": "257"
}