{
    "id": "175",
    "name": "Micha Morales",
    "nationality": "Netherlands",
    "categories": [
        "Longsword (Mixed & Men's, Steel)",
        "Rapier and Dagger (Mixed, Steel)",
        "Sabre (Mixed & Men's, Steel)",
        "Single Rapier (Mixed, Steel)",
        "Singlestick (Mixed)"
    ],
    "ratings": [
        "1392.3",
        "977.7",
        "1078.5",
        "1103.2",
        "1216.4"
    ],
    "rankings": [
        "1014",
        "1110",
        "1335",
        "936",
        "236"
    ],
    "club_id": "52"
}