{
    "id": "6643",
    "name": "Maurizio Viaro",
    "nationality": "Italy",
    "categories": [
        "Longsword (Mixed & Men's, Steel)",
        "Sabre (Mixed & Men's, Steel)",
        "Sidesword (Mixed, Steel)",
        "Single Rapier (Mixed, Steel)",
        "Sword and Buckler (Mixed, Steel)"
    ],
    "ratings": [
        "914.3",
        "1321.2",
        "1063",
        "850.6",
        "938.7"
    ],
    "rankings": [
        "5940",
        "524",
        "467",
        "1600",
        "1448"
    ],
    "club_id": "351"
}