{
    "id": "11635",
    "name": "Mac Siruta",
    "nationality": "United States",
    "categories": [
        "Longsword (Mixed & Men's, Nylon)",
        "Longsword (Mixed & Men's, Steel)",
        "Rapier and Dagger (Mixed, Steel)",
        "Sabre (Mixed & Men's, Steel)",
        "Singlestick (Mixed)"
    ],
    "ratings": [
        "1239.6",
        "1226.6",
        "905.2",
        "1113.9",
        "1014.4"
    ],
    "rankings": [
        "220",
        "2332",
        "1286",
        "1212",
        "469"
    ],
    "club_id": "397"
}