{
    "id": "96",
    "name": "AIMA Roma 2017",
    "date": "March 3",
    "country": "Italy",
    "state": "",
    "city": "Rome",
    "categories": [
        "Mixed Steel Longsword",
        "Mixed Steel Rapier & Dagger",
        "Mixed Steel Single Rapier",
        "Women's Steel Longsword"
    ],
    "participants": [
        "2189",
        "2205",
        "2202",
        "2193",
        "2194",
        "1021",
        "1931",
        "2199",
        "990",
        "983",
        "1019",
        "991",
        "992",
        "993",
        "994",
        "532",
        "1288",
        "1850",
        "1902",
        "2192",
        "1933",
        "1938",
        "1940",
        "1945",
        "2200",
        "2198",
        "2206",
        "2207",
        "2208",
        "2209",
        "2210",
        "2211",
        "2212",
        "2224",
        "2225",
        "2226",
        "2227",
        "2228",
        "2229",
        "2230",
        "2231",
        "2217",
        "2218",
        "2219",
        "2220",
        "2221",
        "2222",
        "2203",
        "2204",
        "2233",
        "2234",
        "2236",
        "2237",
        "2245",
        "1100",
        "1101",
        "1102",
        "2057",
        "2197",
        "2190",
        "581",
        "2213",
        "2214",
        "2215",
        "2216",
        "1910",
        "1041",
        "989",
        "1048",
        "1032",
        "985",
        "1051",
        "1002",
        "1004",
        "2191",
        "1918",
        "1560",
        "2238",
        "2239",
        "2240",
        "1039",
        "2232",
        "158",
        "1011",
        "2195",
        "2235",
        "530",
        "2196",
        "2223",
        "244",
        "2201",
        "219",
        "209",
        "196",
        "579",
        "1359",
        "216",
        "10",
        "234",
        "197",
        "1180",
        "346",
        "438"
    ]
}