{
    "id": "5",
    "name": "Vasaslaget 2016",
    "date": "February 26",
    "country": "Sweden",
    "state": "",
    "city": "Uppsala",
    "categories": [
        "Mixed Steel Arming Sword & Buckler",
        "Mixed Steel Longsword"
    ],
    "participants": [
        "192",
        "243",
        "244",
        "219",
        "224",
        "237",
        "235",
        "50",
        "249",
        "6",
        "78",
        "107",
        "226",
        "231",
        "240",
        "241",
        "113",
        "239",
        "232",
        "225",
        "222",
        "223",
        "24",
        "234",
        "247",
        "227",
        "106",
        "92",
        "71",
        "76",
        "77",
        "117",
        "238",
        "245",
        "228",
        "197",
        "2248",
        "96",
        "98",
        "236",
        "246",
        "233",
        "248",
        "229"
    ]
}