{
    "id": "1681",
    "name": "SoCal Swordfight 2022",
    "date": "February 18",
    "country": "United States",
    "state": "California",
    "city": "Long Beach",
    "categories": [
        "Mixed Steel Longsword",
        "Mixed Steel Longsword",
        "Mixed Steel Rapier & Dagger",
        "Mixed Steel Sabre",
        "Mixed Steel Single Rapier",
        "Mixed Steel Smallsword",
        "Women's Steel Longsword"
    ],
    "participants": [
        "9989",
        "773",
        "8472",
        "163",
        "8692",
        "219",
        "7676",
        "10011",
        "10016",
        "1243",
        "1973",
        "3156",
        "10009",
        "9554",
        "9069",
        "9983",
        "9056",
        "7922",
        "7925",
        "8873",
        "7346",
        "7353",
        "9651",
        "477",
        "848",
        "969",
        "10010",
        "8374",
        "9555",
        "9556",
        "9557",
        "9095",
        "9573",
        "811",
        "1265",
        "9058",
        "10013",
        "778",
        "1276",
        "7261",
        "7234",
        "9981",
        "10036",
        "10037",
        "10038",
        "9072",
        "9049",
        "9998",
        "845",
        "7262",
        "7259",
        "7228",
        "10024",
        "10031",
        "10032",
        "10014",
        "10015",
        "9096",
        "9675",
        "9051",
        "9052",
        "10025",
        "10026",
        "10027",
        "10028",
        "9047",
        "2001",
        "1417",
        "820",
        "7236",
        "7237",
        "10022",
        "9984",
        "8090",
        "7226",
        "10012",
        "6077",
        "3518",
        "5128",
        "5131",
        "5133",
        "1974",
        "1986",
        "7240",
        "7242",
        "7247",
        "813",
        "831",
        "876",
        "10004",
        "10039",
        "9071",
        "9073",
        "9676",
        "267",
        "10017",
        "499",
        "9558",
        "9560",
        "9562",
        "10030",
        "10023",
        "799",
        "489",
        "470",
        "9563",
        "9971",
        "775",
        "6234",
        "3094",
        "2142",
        "2627",
        "9091",
        "10019",
        "10020",
        "10021",
        "10357",
        "7272",
        "9995",
        "5144",
        "1261",
        "10018",
        "7381",
        "842",
        "779",
        "803",
        "405",
        "7246",
        "7250",
        "7251",
        "5124",
        "10033",
        "10034",
        "9077",
        "9081",
        "1975",
        "1985",
        "10035",
        "6226",
        "6246",
        "472",
        "496",
        "9564",
        "10029",
        "9990",
        "796",
        "797",
        "9571"
    ]
}