{
    "id": "1447",
    "name": "Open Golden Forests Tournament Spring 2019",
    "date": "March 30",
    "country": "Russia",
    "state": "",
    "city": "Moscow",
    "categories": [
        "Mixed Classical Dueling Singlesword",
        "Mixed Steel Sabre",
        "Mixed Steel Sabre",
        "Mixed Steel Sabre"
    ],
    "participants": [
        "1900",
        "2565",
        "7689",
        "7698",
        "7615",
        "7696",
        "6983",
        "6882",
        "7008",
        "7688",
        "7489",
        "2572",
        "2564",
        "2528",
        "2551",
        "1889",
        "1131",
        "2560",
        "1888",
        "1884",
        "2525",
        "6185",
        "6874",
        "7694",
        "7692",
        "7481",
        "7487",
        "6979",
        "6969",
        "7690",
        "2522",
        "2523",
        "6976",
        "7037",
        "5490",
        "6977",
        "6982",
        "6985",
        "1885",
        "524",
        "1866",
        "1890",
        "2521",
        "2553",
        "2539",
        "7488",
        "7697",
        "2566",
        "193",
        "2453",
        "7693",
        "7700",
        "7701",
        "2541",
        "2542",
        "2545",
        "2536",
        "1887",
        "196",
        "579",
        "1359",
        "1839",
        "2429",
        "6875",
        "7699",
        "7691",
        "7695"
    ]
}