{
    "id": "1474",
    "name": "A Midsummer Fight's Dream 2019",
    "date": "June 15",
    "country": "United Kingdom",
    "state": "",
    "city": "Oxford",
    "categories": [
        "Mixed Nylon Dussack",
        "Mixed Steel Longsword",
        "Mixed Steel Single Sidesword"
    ],
    "participants": [
        "6285",
        "6058",
        "7844",
        "2880",
        "2892",
        "5928",
        "5975",
        "7845",
        "6288",
        "7849",
        "7851",
        "2888",
        "7776",
        "7576",
        "3371",
        "3502",
        "7850",
        "7846",
        "7847",
        "7848",
        "7852",
        "6705",
        "6706",
        "4680",
        "7160",
        "3248",
        "3250",
        "2891",
        "6291"
    ]
}