{
    "id": "1690",
    "name": "Wild Boar Tusk",
    "date": "October 23",
    "country": "Poland",
    "state": "",
    "city": "Kielce",
    "categories": [
        "Mixed Steel Rapier & Dagger",
        "Mixed Steel Sabre",
        "Mixed Steel Smallsword",
        "Mixed Steel Smallsword",
        "Women's Steel Rapier & Dagger",
        "Women's Steel Sabre"
    ],
    "participants": [
        "6493",
        "7304",
        "9318",
        "12221",
        "451",
        "6588",
        "3263",
        "4823",
        "8772",
        "9326",
        "6490",
        "4769",
        "10205",
        "9328",
        "8559",
        "8565",
        "9323",
        "9892",
        "3477",
        "8794",
        "8796",
        "8764",
        "9920",
        "9774",
        "8762",
        "9973",
        "9974",
        "4870",
        "10206",
        "8792",
        "9977",
        "582",
        "9775",
        "10207",
        "10209",
        "10210",
        "10211",
        "10212",
        "10213",
        "10214",
        "10203",
        "7475",
        "6591",
        "6592",
        "7303",
        "10204",
        "9315",
        "9321",
        "4893",
        "9976",
        "7301",
        "7305",
        "9972",
        "6860",
        "6865",
        "3253",
        "10208",
        "2499",
        "7874",
        "9410",
        "9417"
    ]
}