{
    "id": "1930",
    "name": "World Broadsword Cup 2023",
    "date": "October 27",
    "country": "Australia",
    "state": "South Australia",
    "city": "Adelaide",
    "categories": [
        "Mixed Steel Basket-Hilted Broadsword",
        "Mixed Steel Longsword",
        "Mixed Steel Sabre"
    ],
    "participants": [
        "8065",
        "8077",
        "10602",
        "10603",
        "10604",
        "10605",
        "10606",
        "10610",
        "10616",
        "12802",
        "12880",
        "12881",
        "12882",
        "12883",
        "1773",
        "1797",
        "5038",
        "12877",
        "3313",
        "6698",
        "6699",
        "1798",
        "10615",
        "10617",
        "12878",
        "10600",
        "10601",
        "2748",
        "10356",
        "12879",
        "8080",
        "6795",
        "6157"
    ]
}